packetraven/__init__.py
packetraven/__main__.py
packetraven/model.py
packetraven/predicts.py
packetraven/configuration/__init__.py
packetraven/configuration/base.py
packetraven/configuration/credentials.py
packetraven/configuration/prediction.py
packetraven/configuration/run.py
packetraven/configuration/text.py
packetraven/connections/__init__.py
packetraven/connections/base.py
packetraven/connections/file.py
packetraven/connections/internet.py
packetraven/connections/serial.py
packetraven/gui/__init__.py
packetraven/gui/base.py
packetraven/gui/plotting.py
packetraven/packets/__init__.py
packetraven/packets/base.py
packetraven/packets/parsing.py
packetraven/packets/structures.py
packetraven/packets/tracks.py
packetraven/packets/writer.py
packetraven-2.1.0.dist-info/LICENSE
packetraven-2.1.0.dist-info/METADATA
packetraven-2.1.0.dist-info/WHEEL
packetraven-2.1.0.dist-info/entry_points.txt
packetraven-2.1.0.dist-info/top_level.txt
packetraven-2.1.0.dist-info/RECORD
