Metadata-Version: 2.1
Name: packetraven
Version: 2.1.0
Summary: Telemetry dashboard for APRS packets from TNC, https://aprs.fi, and PostGIS
Author-email: Zach Burnett <zachary.r.burnett@gmail.com>
License: GNU GENERAL PUBLIC LICENSE
Project-URL: repository, https://github.com/UMDBPP/packetraven
Project-URL: documentation, https://packetraven.readthedocs.io
Requires-Python: >=3.8
License-File: LICENSE
Requires-Dist: aprslib
Requires-Dist: backoff
Requires-Dist: humanize
Requires-Dist: numpy
Requires-Dist: pandas
Requires-Dist: pyserial
Requires-Dist: geojson
Requires-Dist: fastkml
Requires-Dist: matplotlib
Requires-Dist: pyproj
Requires-Dist: pyyaml
Requires-Dist: requests
Requires-Dist: shapely
Requires-Dist: sshtunnel
Requires-Dist: tablecrow (>=1.4.3)
Requires-Dist: teek
Requires-Dist: typepigeon (>=1.0.13)
Requires-Dist: typer
Provides-Extra: docs
Requires-Dist: m2r2 ; extra == 'docs'
Requires-Dist: sphinx ; extra == 'docs'
Requires-Dist: sphinx-rtd-theme ; extra == 'docs'
Requires-Dist: sphinxcontrib-programoutput ; extra == 'docs'
Provides-Extra: test
Requires-Dist: pytest ; extra == 'test'
Requires-Dist: pytest-cov ; extra == 'test'
Requires-Dist: pytest-mock ; extra == 'test'
Requires-Dist: pytest-xdist ; extra == 'test'
